emat/__init__.py
emat/_pkg_constants.py
emat/configuration.py
emat/exceptions.py
emat/styles.py
emat/versions.py
emat/analysis/__init__.py
emat/analysis/cart.py
emat/analysis/contrast.py
emat/analysis/discovery.py
emat/analysis/explore.py
emat/analysis/feature_scoring.py
emat/analysis/prim.py
emat/analysis/visual_distribution.py
emat/analysis/widgets.py
emat/analysis/explore_2/__init__.py
emat/analysis/explore_2/explore_base.py
emat/analysis/explore_2/explore_visualizer.py
emat/analysis/explore_2/menu.py
emat/analysis/explore_2/threeway.py
emat/analysis/explore_2/twoway.py
emat/analysis/explore_2/components/__init__.py
emat/analysis/explore_2/components/three_dim_figure.py
emat/analysis/explore_2/components/two_dim_figure.py
emat/database/__init__.py
emat/database/database.py
emat/database/dynamo/__init__.py
emat/database/dynamo/local_server.py
emat/database/dynamo/serialization.py
emat/database/dynamo/storage.py
emat/database/kvstore/__init__.py
emat/database/kvstore/storage.py
emat/database/kvstore/stores.py
emat/database/kvstore/yaml_dumper.py
emat/database/sqlite/__init__.py
emat/database/sqlite/callback.py
emat/database/sqlite/emat_db_init.sql
emat/database/sqlite/emat_db_init_views.sql
emat/database/sqlite/emat_db_rebuild.sql
emat/database/sqlite/meta_model.sql
emat/database/sqlite/reset.sql
emat/database/sqlite/scope.sql
emat/database/sqlite/sql_queries.py
emat/database/sqlite/sqlite_db.py
emat/examples/__init__.py
emat/examples/gbnrtc/buffalo.csv
emat/examples/gbnrtc/gbnrtc_model_config.yaml
emat/examples/gbnrtc/gbnrtc_scope.yaml
emat/examples/gbnrtc/archive/scp_GBNRTC/exp_001.csv
emat/examples/gbnrtc/archive/scp_GBNRTC/exp_002.csv
emat/examples/gbnrtc/archive/scp_GBNRTC/exp_003.csv
emat/examples/gbnrtc/archive/scp_GBNRTC/exp_004.csv
emat/examples/gbnrtc/archive/scp_GBNRTC/exp_005.csv
emat/examples/gbnrtc/archive/scp_GBNRTC/exp_001/Outputs/CorridorMeasures.csv
emat/examples/gbnrtc/archive/scp_GBNRTC/exp_001/Outputs/District_OD.csv
emat-0.6.1.dist-info/LICENSE
emat-0.6.1.dist-info/METADATA
emat-0.6.1.dist-info/WHEEL
emat-0.6.1.dist-info/entry_points.txt
emat-0.6.1.dist-info/top_level.txt
emat-0.6.1.dist-info/RECORD
